certcv/__init__.py
certcv/certcv.py
certcv-0.1.2.dist-info/LICENSE
certcv-0.1.2.dist-info/METADATA
certcv-0.1.2.dist-info/WHEEL
certcv-0.1.2.dist-info/entry_points.txt
certcv-0.1.2.dist-info/top_level.txt
certcv-0.1.2.dist-info/RECORD
