Metadata-Version: 2.1
Name: certcv
Version: 0.1.2
Summary: "A copy/paster quick-tool for adding private keys and certificate keys to the openVPN configuration file."
Home-page: https://github.com/LukeHankey/certcv
Author: Luke Hankey
Author-email: lukehankey@gmail.com
License: MIT
Project-URL: Bug Tracker, https://github.com/LukeHankey/certcv/issues
Classifier: License :: OSI Approved :: MIT License
Classifier: Programming Language :: Python :: 3
Classifier: Programming Language :: Python :: 3 :: Only
Classifier: Programming Language :: Python :: 3.10
Classifier: Operating System :: OS Independent
Requires-Python: >=3.10
License-File: LICENSE
